wsgitypes/__init__.py
wsgitypes/py.typed
wsgitypes-0.0.4.dist-info/LICENSE
wsgitypes-0.0.4.dist-info/METADATA
wsgitypes-0.0.4.dist-info/WHEEL
wsgitypes-0.0.4.dist-info/top_level.txt
wsgitypes-0.0.4.dist-info/RECORD
