Metadata-Version: 2.1
Name: wsgitypes
Version: 0.0.4
Summary: MyPy types for WSGI
Home-page: https://github.com/shabbyrobe/wsgitypes
Author: Blake Williams
Author-email: code@shabbyrobe.org
License: MIT
Platform: UNKNOWN
Classifier: Development Status :: 3 - Alpha
Classifier: License :: OSI Approved :: MIT License
Classifier: Programming Language :: Python :: 3.7
Requires-Python: >=3.7
Requires-Dist: mypy (>=0.730)
Requires-Dist: typing-extensions
